mmm/v1/mmm.proto
mmm/v1/mmm_pb2.py
mmm/v1/common/date_interval.proto
mmm/v1/common/date_interval_pb2.py
mmm/v1/common/estimate.proto
mmm/v1/common/estimate_pb2.py
mmm/v1/common/kpi_type.proto
mmm/v1/common/kpi_type_pb2.py
mmm/v1/common/target_metric.proto
mmm/v1/common/target_metric_pb2.py
mmm/v1/fit/model_fit.proto
mmm/v1/fit/model_fit_pb2.py
mmm/v1/marketing/marketing_data.proto
mmm/v1/marketing/marketing_data_pb2.py
mmm/v1/marketing/new_marketing_data.proto
mmm/v1/marketing/new_marketing_data_pb2.py
mmm/v1/marketing/analysis/marketing_analysis.proto
mmm/v1/marketing/analysis/marketing_analysis_pb2.py
mmm/v1/marketing/analysis/media_analysis.proto
mmm/v1/marketing/analysis/media_analysis_pb2.py
mmm/v1/marketing/analysis/non_media_analysis.proto
mmm/v1/marketing/analysis/non_media_analysis_pb2.py
mmm/v1/marketing/analysis/outcome.proto
mmm/v1/marketing/analysis/outcome_pb2.py
mmm/v1/marketing/analysis/response_curve.proto
mmm/v1/marketing/analysis/response_curve_pb2.py
mmm/v1/marketing/optimization/budget_optimization.proto
mmm/v1/marketing/optimization/budget_optimization_pb2.py
mmm/v1/marketing/optimization/constraints.proto
mmm/v1/marketing/optimization/constraints_pb2.py
mmm/v1/marketing/optimization/marketing_optimization.proto
mmm/v1/marketing/optimization/marketing_optimization_pb2.py
mmm/v1/marketing/optimization/reach_frequency_optimization.proto
mmm/v1/marketing/optimization/reach_frequency_optimization_pb2.py
mmm/v1/model/mmm_kernel.proto
mmm/v1/model/mmm_kernel_pb2.py
mmm/v1/model/meridian/meridian_model.proto
mmm/v1/model/meridian/meridian_model_pb2.py
mmm/v1/model/meridian/eda/eda_spec.proto
mmm/v1/model/meridian/eda/eda_spec_pb2.py
mmm_proto_schema-1.1.1.dist-info/licenses/LICENSE
mmm_proto_schema-1.1.1.dist-info/METADATA
mmm_proto_schema-1.1.1.dist-info/WHEEL
mmm_proto_schema-1.1.1.dist-info/top_level.txt
mmm_proto_schema-1.1.1.dist-info/RECORD
