Metadata-Version: 2.4
Name: mmm-proto-schema
Version: 1.1.1
Summary: A Meridian submodule for MMM model representation in protobuf form.
Author-email: The Meridian Authors <no-reply@google.com>
Project-URL: homepage, https://github.com/google/meridian/tree/main/proto
Project-URL: repository, https://github.com/google/meridian/tree/main/proto
Project-URL: changelog, https://github.com/google/meridian/tree/main/proto/CHANGELOG.md
Project-URL: documentation, https://developers.google.com/meridian/docs/user-guide/mmm-unified-schema
Keywords: mmm,protobuf
Classifier: Programming Language :: Python :: 3
Classifier: Programming Language :: Python :: 3 :: Only
Classifier: Topic :: Other/Nonlisted Topic
Classifier: Topic :: Scientific/Engineering :: Information Analysis
Requires-Python: >=3.10
License-File: LICENSE
Requires-Dist: googleapis-common-protos
Requires-Dist: protobuf
Requires-Dist: tensorflow
Dynamic: license-file
